abx_plugin_git/__init__.py
abx_plugin_git/binaries.py
abx_plugin_git/config.py
abx_plugin_git/extractors.py
abx_plugin_git/git.py
abx_plugin_git-2024.10.28.dist-info/METADATA
abx_plugin_git-2024.10.28.dist-info/WHEEL
abx_plugin_git-2024.10.28.dist-info/entry_points.txt
abx_plugin_git-2024.10.28.dist-info/RECORD
